generate_temp_table_sql/__init__.py
generate_temp_table_sql/cli.py
generate_temp_table_sql/constants.py
generate_temp_table_sql/sql_generator.py
tests/__init__.py
tests/test_sql_generator.py
generate_temp_table_sql-0.4.5.dist-info/LICENSE.txt
generate_temp_table_sql-0.4.5.dist-info/METADATA
generate_temp_table_sql-0.4.5.dist-info/WHEEL
generate_temp_table_sql-0.4.5.dist-info/entry_points.txt
generate_temp_table_sql-0.4.5.dist-info/top_level.txt
generate_temp_table_sql-0.4.5.dist-info/RECORD
