Metadata-Version: 2.1
Name: generate-temp-table-sql
Version: 0.4.5
Summary: A package to generate SQL statements from CSV files
Home-page: https://github.com/ryanwaldorf/generate_temp_table_sql
Author: Ryan Waldorf
Author-email: ryan@ryanwaldorf.com
License: UNKNOWN
Platform: UNKNOWN
Classifier: Programming Language :: Python :: 3
Classifier: License :: OSI Approved :: MIT License
Classifier: Operating System :: OS Independent
Requires-Python: >=3.6
License-File: LICENSE.txt
Requires-Dist: pandas
